seasnake/__init__.py
seasnake_bite-0.0.15.dist-info/licenses/LICENSE
seasnake_bite-0.0.15.dist-info/METADATA
seasnake_bite-0.0.15.dist-info/WHEEL
seasnake_bite-0.0.15.dist-info/top_level.txt
seasnake_bite-0.0.15.dist-info/RECORD
